alectiokmscli/__init__.py
alectiokmscli/alectio_auth.py
alectio_kms-1.0.0.dist-info/METADATA
alectio_kms-1.0.0.dist-info/WHEEL
alectio_kms-1.0.0.dist-info/entry_points.txt
alectio_kms-1.0.0.dist-info/top_level.txt
alectio_kms-1.0.0.dist-info/RECORD
